kahi_wikidata_affiliations/Kahi_wikidata_affiliations.py
kahi_wikidata_affiliations/__init__.py
kahi_wikidata_affiliations/_version.py
Kahi_wikidata_affiliations-0.1.1b0.dist-info/LICENSE
Kahi_wikidata_affiliations-0.1.1b0.dist-info/METADATA
Kahi_wikidata_affiliations-0.1.1b0.dist-info/WHEEL
Kahi_wikidata_affiliations-0.1.1b0.dist-info/top_level.txt
Kahi_wikidata_affiliations-0.1.1b0.dist-info/RECORD
